README.md
setup.py
bupt_api/__init__.py
bupt_api/card.py
bupt_api/jwql.py
bupt_api/jwxt.py
bupt_api/login.py
bupt_api/my.py
bupt_api.egg-info/PKG-INFO
bupt_api.egg-info/SOURCES.txt
bupt_api.egg-info/dependency_links.txt
bupt_api.egg-info/requires.txt
bupt_api.egg-info/top_level.txt