Metadata-Version: 1.0
Name: bupt-api
Version: 0.3.0
Summary: 北邮的一些api,陆续添加中
Home-page: https://github.com/WangZeKun/bupt-api
Author: zekin
Author-email: wzekin@gmail.com
License: UNKNOWN
Platform: any
